{
  "project_info": {
    "project_number": "826855507886",
    "project_id": "todo-demo-app-ddeaa",
    "storage_bucket": "todo-demo-app-ddeaa.appspot.com"
  },
  "client": [
    {
      "client_info": {
        "mobilesdk_app_id": "1:826855507886:android:0e990f60333df14701ea3f",
        "android_client_info": {
          "package_name": "com.todo.app"
        }
      },
      "oauth_client": [],
      "api_key": [
        {
          "current_key": "AIzaSyCLGDU6UpHcshkeZrKThDd7FjkY8mTjFdg"
        }
      ],
      "services": {
        "appinvite_service": {
          "other_platform_oauth_client": []
        }
      }
    }
  ],
  "configuration_version": "1"
}